gstudios-0.1.0.dist-info/METADATA
gstudios-0.1.0.dist-info/WHEEL
gstudios-0.1.0.dist-info/entry_points.txt
gstudios-0.1.0.dist-info/licenses/LICENSE
gstudios/__about__.py
gstudios/__init__.py
gstudios-0.1.0.dist-info/RECORD
