Metadata-Version: 2.1
Name: gstudios
Version: 0.1.0
Summary: Python package for GStudios services.
Keywords: gstudios,api,service
Author-Email: Garrett HE <garrett.he@outlook.com>
License: BSD-3-Clause
Classifier: Development Status :: 2 - Pre-Alpha
Classifier: Programming Language :: Python :: 3
Classifier: Programming Language :: Python :: 3.10
Classifier: Programming Language :: Python :: 3.11
Classifier: Programming Language :: Python :: 3.12
Classifier: Programming Language :: Python :: 3.13
Project-URL: homepage, https://github.com/garrett-he/python-gstudios
Project-URL: repository, https://github.com/garrett-he/python-gstudios.git
Project-URL: changelog, https://github.com/garrett-he/python-gstudios/blob/main/CHANGELOG.md
Requires-Python: >=3.10
